cadence_sdk/__init__.py
cadence_sdk/base/__init__.py
cadence_sdk/base/agent.py
cadence_sdk/base/loggable.py
cadence_sdk/base/metadata.py
cadence_sdk/base/plugin.py
cadence_sdk/decorators/__init__.py
cadence_sdk/decorators/schema.py
cadence_sdk/decorators/tool.py
cadence_sdk/examples/__init__.py
cadence_sdk/examples/template_plugin/__init__.py
cadence_sdk/examples/template_plugin/agent.py
cadence_sdk/examples/template_plugin/plugin.py
cadence_sdk/registry/__init__.py
cadence_sdk/registry/contracts.py
cadence_sdk/registry/plugin_registry.py
cadence_sdk/types/__init__.py
cadence_sdk/types/messages.py
cadence_sdk/types/state.py
cadence_sdk/utils/__init__.py
cadence_sdk/utils/directory_discovery.py
cadence_sdk/utils/environment_discovery.py
cadence_sdk/utils/helpers.py
cadence_sdk/utils/installers.py
cadence_sdk/utils/tool_conversion.py
cadence_sdk/utils/validation.py
cadence_sdk-1.3.3.dist-info/METADATA
cadence_sdk-1.3.3.dist-info/WHEEL
cadence_sdk-1.3.3.dist-info/licenses/LICENSE
cadence_sdk-1.3.3.dist-info/RECORD
