Metadata-Version: 2.4
Name: cadence-sdk
Version: 1.3.3
Summary: Cadence SDK - To building custom AI agent plugins for Cadence AI Framework
License: MIT
License-File: LICENSE
Keywords: ai,agents,cadence-ai,cadence_sdk,langchain,langgraph,plugins
Author: Jonas Kahn
Author-email: me@ifelse.one
Requires-Python: >=3.13,<3.14
Classifier: Intended Audience :: Developers
Classifier: License :: OSI Approved :: MIT License
Classifier: Programming Language :: Python :: 3
Classifier: Programming Language :: Python :: 3.13
Classifier: Topic :: Software Development :: Libraries :: Python Modules
Classifier: Topic :: Scientific/Engineering :: Artificial Intelligence
Provides-Extra: dev
Requires-Dist: black (>=25.1.0,<26.0.0) ; extra == "dev"
Requires-Dist: isort (>=6.0.1,<7.0.0) ; extra == "dev"
Requires-Dist: langchain-core (>=0.3.74,<0.4.0)
Requires-Dist: langgraph (>=0.6.5,<0.7.0)
Requires-Dist: mypy (>=1.17.1,<2.0.0) ; extra == "dev"
Requires-Dist: pre-commit (>=4.3.0,<5.0.0) ; extra == "dev"
Requires-Dist: pydantic (>=2.11.7,<3.0.0)
Requires-Dist: pytest (>=8.4.1,<9.0.0) ; extra == "dev"
Requires-Dist: pytest-asyncio (>=1.1.0,<2.0.0) ; extra == "dev"
Requires-Dist: pytest-cov (>=6.2.1,<7.0.0) ; extra == "dev"
Requires-Dist: pytest-mock (>=3.14.1,<4.0.0) ; extra == "dev"
Requires-Dist: ruff (>=0.12.9,<0.13.0) ; extra == "dev"
Requires-Dist: typing-extensions (>=4.14.1,<5.0.0)
Project-URL: Documentation, https://cadence_sdk.readthedocs.io/
Project-URL: Homepage, https://github.com/jonaskahn/cadence-sdk
Project-URL: Repository, https://github.com/jonaskahn/cadence-sdk.git
Project-URL: issues, https://github.com/jonaskahn/cadence-sdk/issues
